<annotation>
	<folder>images</folder>
	<filename>0_1.jpg</filename>
	<path>C:\Users\Elizaveta\Desktop\desktop\Projects\calculator_project\new_try\images\0_1.jpg</path>
	<source>
		<database>Unknown</database>
	</source>
	<size>
		<width>4032</width>
		<height>3024</height>
		<depth>3</depth>
	</size>
	<segmented>0</segmented>
	<object>
		<name>0</name>
		<pose>Unspecified</pose>
		<truncated>0</truncated>
		<difficult>0</difficult>
		<bndbox>
			<xmin>281</xmin>
			<ymin>549</ymin>
			<xmax>394</xmax>
			<ymax>711</ymax>
		</bndbox>
	</object>
	<object>
		<name>0</name>
		<pose>Unspecified</pose>
		<truncated>0</truncated>
		<difficult>0</difficult>
		<bndbox>
			<xmin>500</xmin>
			<ymin>561</ymin>
			<xmax>612</xmax>
			<ymax>718</ymax>
		</bndbox>
	</object>
	<object>
		<name>0</name>
		<pose>Unspecified</pose>
		<truncated>0</truncated>
		<difficult>0</difficult>
		<bndbox>
			<xmin>806</xmin>
			<ymin>555</ymin>
			<xmax>931</xmax>
			<ymax>699</ymax>
		</bndbox>
	</object>
	<object>
		<name>0</name>
		<pose>Unspecified</pose>
		<truncated>0</truncated>
		<difficult>0</difficult>
		<bndbox>
			<xmin>1069</xmin>
			<ymin>555</ymin>
			<xmax>1194</xmax>
			<ymax>711</ymax>
		</bndbox>
	</object>
	<object>
		<name>0</name>
		<pose>Unspecified</pose>
		<truncated>0</truncated>
		<difficult>0</difficult>
		<bndbox>
			<xmin>1362</xmin>
			<ymin>555</ymin>
			<xmax>1481</xmax>
			<ymax>711</ymax>
		</bndbox>
	</object>
	<object>
		<name>0</name>
		<pose>Unspecified</pose>
		<truncated>0</truncated>
		<difficult>0</difficult>
		<bndbox>
			<xmin>1675</xmin>
			<ymin>561</ymin>
			<xmax>1812</xmax>
			<ymax>736</ymax>
		</bndbox>
	</object>
	<object>
		<name>0</name>
		<pose>Unspecified</pose>
		<truncated>0</truncated>
		<difficult>0</difficult>
		<bndbox>
			<xmin>2006</xmin>
			<ymin>580</ymin>
			<xmax>2112</xmax>
			<ymax>736</ymax>
		</bndbox>
	</object>
	<object>
		<name>0</name>
		<pose>Unspecified</pose>
		<truncated>0</truncated>
		<difficult>0</difficult>
		<bndbox>
			<xmin>2275</xmin>
			<ymin>574</ymin>
			<xmax>2387</xmax>
			<ymax>718</ymax>
		</bndbox>
	</object>
	<object>
		<name>0</name>
		<pose>Unspecified</pose>
		<truncated>0</truncated>
		<difficult>0</difficult>
		<bndbox>
			<xmin>2537</xmin>
			<ymin>586</ymin>
			<xmax>2631</xmax>
			<ymax>743</ymax>
		</bndbox>
	</object>
	<object>
		<name>0</name>
		<pose>Unspecified</pose>
		<truncated>0</truncated>
		<difficult>0</difficult>
		<bndbox>
			<xmin>2781</xmin>
			<ymin>586</ymin>
			<xmax>2906</xmax>
			<ymax>743</ymax>
		</bndbox>
	</object>
	<object>
		<name>0</name>
		<pose>Unspecified</pose>
		<truncated>0</truncated>
		<difficult>0</difficult>
		<bndbox>
			<xmin>3137</xmin>
			<ymin>599</ymin>
			<xmax>3244</xmax>
			<ymax>743</ymax>
		</bndbox>
	</object>
	<object>
		<name>0</name>
		<pose>Unspecified</pose>
		<truncated>0</truncated>
		<difficult>0</difficult>
		<bndbox>
			<xmin>3425</xmin>
			<ymin>605</ymin>
			<xmax>3556</xmax>
			<ymax>774</ymax>
		</bndbox>
	</object>
	<object>
		<name>0</name>
		<pose>Unspecified</pose>
		<truncated>0</truncated>
		<difficult>0</difficult>
		<bndbox>
			<xmin>3662</xmin>
			<ymin>611</ymin>
			<xmax>3787</xmax>
			<ymax>774</ymax>
		</bndbox>
	</object>
	<object>
		<name>0</name>
		<pose>Unspecified</pose>
		<truncated>0</truncated>
		<difficult>0</difficult>
		<bndbox>
			<xmin>3631</xmin>
			<ymin>874</ymin>
			<xmax>3756</xmax>
			<ymax>1005</ymax>
		</bndbox>
	</object>
	<object>
		<name>0</name>
		<pose>Unspecified</pose>
		<truncated>0</truncated>
		<difficult>0</difficult>
		<bndbox>
			<xmin>3387</xmin>
			<ymin>868</ymin>
			<xmax>3487</xmax>
			<ymax>1005</ymax>
		</bndbox>
	</object>
	<object>
		<name>0</name>
		<pose>Unspecified</pose>
		<truncated>0</truncated>
		<difficult>0</difficult>
		<bndbox>
			<xmin>3081</xmin>
			<ymin>855</ymin>
			<xmax>3200</xmax>
			<ymax>999</ymax>
		</bndbox>
	</object>
	<object>
		<name>0</name>
		<pose>Unspecified</pose>
		<truncated>0</truncated>
		<difficult>0</difficult>
		<bndbox>
			<xmin>2812</xmin>
			<ymin>868</ymin>
			<xmax>2912</xmax>
			<ymax>993</ymax>
		</bndbox>
	</object>
	<object>
		<name>0</name>
		<pose>Unspecified</pose>
		<truncated>0</truncated>
		<difficult>0</difficult>
		<bndbox>
			<xmin>2581</xmin>
			<ymin>849</ymin>
			<xmax>2700</xmax>
			<ymax>980</ymax>
		</bndbox>
	</object>
	<object>
		<name>0</name>
		<pose>Unspecified</pose>
		<truncated>0</truncated>
		<difficult>0</difficult>
		<bndbox>
			<xmin>2269</xmin>
			<ymin>843</ymin>
			<xmax>2394</xmax>
			<ymax>993</ymax>
		</bndbox>
	</object>
	<object>
		<name>0</name>
		<pose>Unspecified</pose>
		<truncated>0</truncated>
		<difficult>0</difficult>
		<bndbox>
			<xmin>2006</xmin>
			<ymin>849</ymin>
			<xmax>2112</xmax>
			<ymax>999</ymax>
		</bndbox>
	</object>
	<object>
		<name>0</name>
		<pose>Unspecified</pose>
		<truncated>0</truncated>
		<difficult>0</difficult>
		<bndbox>
			<xmin>1675</xmin>
			<ymin>836</ymin>
			<xmax>1800</xmax>
			<ymax>986</ymax>
		</bndbox>
	</object>
	<object>
		<name>0</name>
		<pose>Unspecified</pose>
		<truncated>0</truncated>
		<difficult>0</difficult>
		<bndbox>
			<xmin>1400</xmin>
			<ymin>836</ymin>
			<xmax>1506</xmax>
			<ymax>986</ymax>
		</bndbox>
	</object>
	<object>
		<name>0</name>
		<pose>Unspecified</pose>
		<truncated>0</truncated>
		<difficult>0</difficult>
		<bndbox>
			<xmin>1087</xmin>
			<ymin>843</ymin>
			<xmax>1206</xmax>
			<ymax>993</ymax>
		</bndbox>
	</object>
	<object>
		<name>0</name>
		<pose>Unspecified</pose>
		<truncated>0</truncated>
		<difficult>0</difficult>
		<bndbox>
			<xmin>800</xmin>
			<ymin>836</ymin>
			<xmax>900</xmax>
			<ymax>993</ymax>
		</bndbox>
	</object>
	<object>
		<name>0</name>
		<pose>Unspecified</pose>
		<truncated>0</truncated>
		<difficult>0</difficult>
		<bndbox>
			<xmin>550</xmin>
			<ymin>836</ymin>
			<xmax>650</xmax>
			<ymax>974</ymax>
		</bndbox>
	</object>
	<object>
		<name>0</name>
		<pose>Unspecified</pose>
		<truncated>0</truncated>
		<difficult>0</difficult>
		<bndbox>
			<xmin>300</xmin>
			<ymin>843</ymin>
			<xmax>406</xmax>
			<ymax>986</ymax>
		</bndbox>
	</object>
	<object>
		<name>0</name>
		<pose>Unspecified</pose>
		<truncated>0</truncated>
		<difficult>0</difficult>
		<bndbox>
			<xmin>319</xmin>
			<ymin>1124</ymin>
			<xmax>425</xmax>
			<ymax>1255</ymax>
		</bndbox>
	</object>
	<object>
		<name>0</name>
		<pose>Unspecified</pose>
		<truncated>0</truncated>
		<difficult>0</difficult>
		<bndbox>
			<xmin>587</xmin>
			<ymin>1093</ymin>
			<xmax>712</xmax>
			<ymax>1249</ymax>
		</bndbox>
	</object>
	<object>
		<name>0</name>
		<pose>Unspecified</pose>
		<truncated>0</truncated>
		<difficult>0</difficult>
		<bndbox>
			<xmin>806</xmin>
			<ymin>1099</ymin>
			<xmax>900</xmax>
			<ymax>1236</ymax>
		</bndbox>
	</object>
	<object>
		<name>0</name>
		<pose>Unspecified</pose>
		<truncated>0</truncated>
		<difficult>0</difficult>
		<bndbox>
			<xmin>1075</xmin>
			<ymin>1099</ymin>
			<xmax>1194</xmax>
			<ymax>1243</ymax>
		</bndbox>
	</object>
	<object>
		<name>0</name>
		<pose>Unspecified</pose>
		<truncated>0</truncated>
		<difficult>0</difficult>
		<bndbox>
			<xmin>1362</xmin>
			<ymin>1105</ymin>
			<xmax>1462</xmax>
			<ymax>1249</ymax>
		</bndbox>
	</object>
	<object>
		<name>0</name>
		<pose>Unspecified</pose>
		<truncated>0</truncated>
		<difficult>0</difficult>
		<bndbox>
			<xmin>1631</xmin>
			<ymin>1093</ymin>
			<xmax>1725</xmax>
			<ymax>1243</ymax>
		</bndbox>
	</object>
	<object>
		<name>0</name>
		<pose>Unspecified</pose>
		<truncated>0</truncated>
		<difficult>0</difficult>
		<bndbox>
			<xmin>1969</xmin>
			<ymin>1105</ymin>
			<xmax>2075</xmax>
			<ymax>1236</ymax>
		</bndbox>
	</object>
	<object>
		<name>0</name>
		<pose>Unspecified</pose>
		<truncated>0</truncated>
		<difficult>0</difficult>
		<bndbox>
			<xmin>2256</xmin>
			<ymin>1111</ymin>
			<xmax>2356</xmax>
			<ymax>1243</ymax>
		</bndbox>
	</object>
	<object>
		<name>0</name>
		<pose>Unspecified</pose>
		<truncated>0</truncated>
		<difficult>0</difficult>
		<bndbox>
			<xmin>2519</xmin>
			<ymin>1099</ymin>
			<xmax>2644</xmax>
			<ymax>1249</ymax>
		</bndbox>
	</object>
	<object>
		<name>0</name>
		<pose>Unspecified</pose>
		<truncated>0</truncated>
		<difficult>0</difficult>
		<bndbox>
			<xmin>2787</xmin>
			<ymin>1105</ymin>
			<xmax>2894</xmax>
			<ymax>1249</ymax>
		</bndbox>
	</object>
	<object>
		<name>0</name>
		<pose>Unspecified</pose>
		<truncated>0</truncated>
		<difficult>0</difficult>
		<bndbox>
			<xmin>3062</xmin>
			<ymin>1111</ymin>
			<xmax>3175</xmax>
			<ymax>1243</ymax>
		</bndbox>
	</object>
	<object>
		<name>0</name>
		<pose>Unspecified</pose>
		<truncated>0</truncated>
		<difficult>0</difficult>
		<bndbox>
			<xmin>3362</xmin>
			<ymin>1124</ymin>
			<xmax>3475</xmax>
			<ymax>1255</ymax>
		</bndbox>
	</object>
	<object>
		<name>0</name>
		<pose>Unspecified</pose>
		<truncated>0</truncated>
		<difficult>0</difficult>
		<bndbox>
			<xmin>3619</xmin>
			<ymin>1111</ymin>
			<xmax>3725</xmax>
			<ymax>1268</ymax>
		</bndbox>
	</object>
	<object>
		<name>0</name>
		<pose>Unspecified</pose>
		<truncated>0</truncated>
		<difficult>0</difficult>
		<bndbox>
			<xmin>3650</xmin>
			<ymin>1361</ymin>
			<xmax>3756</xmax>
			<ymax>1493</ymax>
		</bndbox>
	</object>
	<object>
		<name>0</name>
		<pose>Unspecified</pose>
		<truncated>0</truncated>
		<difficult>0</difficult>
		<bndbox>
			<xmin>3369</xmin>
			<ymin>1368</ymin>
			<xmax>3462</xmax>
			<ymax>1505</ymax>
		</bndbox>
	</object>
	<object>
		<name>0</name>
		<pose>Unspecified</pose>
		<truncated>0</truncated>
		<difficult>0</difficult>
		<bndbox>
			<xmin>3031</xmin>
			<ymin>1355</ymin>
			<xmax>3131</xmax>
			<ymax>1499</ymax>
		</bndbox>
	</object>
	<object>
		<name>0</name>
		<pose>Unspecified</pose>
		<truncated>0</truncated>
		<difficult>0</difficult>
		<bndbox>
			<xmin>2787</xmin>
			<ymin>1355</ymin>
			<xmax>2875</xmax>
			<ymax>1511</ymax>
		</bndbox>
	</object>
	<object>
		<name>0</name>
		<pose>Unspecified</pose>
		<truncated>0</truncated>
		<difficult>0</difficult>
		<bndbox>
			<xmin>2525</xmin>
			<ymin>1349</ymin>
			<xmax>2631</xmax>
			<ymax>1505</ymax>
		</bndbox>
	</object>
	<object>
		<name>0</name>
		<pose>Unspecified</pose>
		<truncated>0</truncated>
		<difficult>0</difficult>
		<bndbox>
			<xmin>2231</xmin>
			<ymin>1349</ymin>
			<xmax>2344</xmax>
			<ymax>1499</ymax>
		</bndbox>
	</object>
	<object>
		<name>0</name>
		<pose>Unspecified</pose>
		<truncated>0</truncated>
		<difficult>0</difficult>
		<bndbox>
			<xmin>1925</xmin>
			<ymin>1355</ymin>
			<xmax>2025</xmax>
			<ymax>1505</ymax>
		</bndbox>
	</object>
	<object>
		<name>0</name>
		<pose>Unspecified</pose>
		<truncated>0</truncated>
		<difficult>0</difficult>
		<bndbox>
			<xmin>1600</xmin>
			<ymin>1355</ymin>
			<xmax>1687</xmax>
			<ymax>1511</ymax>
		</bndbox>
	</object>
	<object>
		<name>0</name>
		<pose>Unspecified</pose>
		<truncated>0</truncated>
		<difficult>0</difficult>
		<bndbox>
			<xmin>1331</xmin>
			<ymin>1355</ymin>
			<xmax>1456</xmax>
			<ymax>1543</ymax>
		</bndbox>
	</object>
	<object>
		<name>0</name>
		<pose>Unspecified</pose>
		<truncated>0</truncated>
		<difficult>0</difficult>
		<bndbox>
			<xmin>1044</xmin>
			<ymin>1361</ymin>
			<xmax>1162</xmax>
			<ymax>1530</ymax>
		</bndbox>
	</object>
	<object>
		<name>0</name>
		<pose>Unspecified</pose>
		<truncated>0</truncated>
		<difficult>0</difficult>
		<bndbox>
			<xmin>806</xmin>
			<ymin>1380</ymin>
			<xmax>900</xmax>
			<ymax>1530</ymax>
		</bndbox>
	</object>
	<object>
		<name>0</name>
		<pose>Unspecified</pose>
		<truncated>0</truncated>
		<difficult>0</difficult>
		<bndbox>
			<xmin>569</xmin>
			<ymin>1374</ymin>
			<xmax>675</xmax>
			<ymax>1530</ymax>
		</bndbox>
	</object>
	<object>
		<name>0</name>
		<pose>Unspecified</pose>
		<truncated>0</truncated>
		<difficult>0</difficult>
		<bndbox>
			<xmin>300</xmin>
			<ymin>1361</ymin>
			<xmax>406</xmax>
			<ymax>1536</ymax>
		</bndbox>
	</object>
	<object>
		<name>0</name>
		<pose>Unspecified</pose>
		<truncated>0</truncated>
		<difficult>0</difficult>
		<bndbox>
			<xmin>287</xmin>
			<ymin>1661</ymin>
			<xmax>394</xmax>
			<ymax>1805</ymax>
		</bndbox>
	</object>
	<object>
		<name>0</name>
		<pose>Unspecified</pose>
		<truncated>0</truncated>
		<difficult>0</difficult>
		<bndbox>
			<xmin>575</xmin>
			<ymin>1661</ymin>
			<xmax>694</xmax>
			<ymax>1811</ymax>
		</bndbox>
	</object>
	<object>
		<name>0</name>
		<pose>Unspecified</pose>
		<truncated>0</truncated>
		<difficult>0</difficult>
		<bndbox>
			<xmin>837</xmin>
			<ymin>1661</ymin>
			<xmax>956</xmax>
			<ymax>1811</ymax>
		</bndbox>
	</object>
	<object>
		<name>0</name>
		<pose>Unspecified</pose>
		<truncated>0</truncated>
		<difficult>0</difficult>
		<bndbox>
			<xmin>1075</xmin>
			<ymin>1655</ymin>
			<xmax>1187</xmax>
			<ymax>1799</ymax>
		</bndbox>
	</object>
	<object>
		<name>0</name>
		<pose>Unspecified</pose>
		<truncated>0</truncated>
		<difficult>0</difficult>
		<bndbox>
			<xmin>1325</xmin>
			<ymin>1655</ymin>
			<xmax>1444</xmax>
			<ymax>1805</ymax>
		</bndbox>
	</object>
	<object>
		<name>0</name>
		<pose>Unspecified</pose>
		<truncated>0</truncated>
		<difficult>0</difficult>
		<bndbox>
			<xmin>1600</xmin>
			<ymin>1649</ymin>
			<xmax>1725</xmax>
			<ymax>1799</ymax>
		</bndbox>
	</object>
	<object>
		<name>0</name>
		<pose>Unspecified</pose>
		<truncated>0</truncated>
		<difficult>0</difficult>
		<bndbox>
			<xmin>1887</xmin>
			<ymin>1630</ymin>
			<xmax>2000</xmax>
			<ymax>1786</ymax>
		</bndbox>
	</object>
	<object>
		<name>0</name>
		<pose>Unspecified</pose>
		<truncated>0</truncated>
		<difficult>0</difficult>
		<bndbox>
			<xmin>2200</xmin>
			<ymin>1630</ymin>
			<xmax>2319</xmax>
			<ymax>1799</ymax>
		</bndbox>
	</object>
	<object>
		<name>0</name>
		<pose>Unspecified</pose>
		<truncated>0</truncated>
		<difficult>0</difficult>
		<bndbox>
			<xmin>2494</xmin>
			<ymin>1636</ymin>
			<xmax>2606</xmax>
			<ymax>1786</ymax>
		</bndbox>
	</object>
	<object>
		<name>0</name>
		<pose>Unspecified</pose>
		<truncated>0</truncated>
		<difficult>0</difficult>
		<bndbox>
			<xmin>2775</xmin>
			<ymin>1649</ymin>
			<xmax>2894</xmax>
			<ymax>1799</ymax>
		</bndbox>
	</object>
	<object>
		<name>0</name>
		<pose>Unspecified</pose>
		<truncated>0</truncated>
		<difficult>0</difficult>
		<bndbox>
			<xmin>3037</xmin>
			<ymin>1636</ymin>
			<xmax>3144</xmax>
			<ymax>1768</ymax>
		</bndbox>
	</object>
	<object>
		<name>0</name>
		<pose>Unspecified</pose>
		<truncated>0</truncated>
		<difficult>0</difficult>
		<bndbox>
			<xmin>3312</xmin>
			<ymin>1611</ymin>
			<xmax>3419</xmax>
			<ymax>1780</ymax>
		</bndbox>
	</object>
	<object>
		<name>0</name>
		<pose>Unspecified</pose>
		<truncated>0</truncated>
		<difficult>0</difficult>
		<bndbox>
			<xmin>3600</xmin>
			<ymin>1624</ymin>
			<xmax>3712</xmax>
			<ymax>1768</ymax>
		</bndbox>
	</object>
	<object>
		<name>0</name>
		<pose>Unspecified</pose>
		<truncated>0</truncated>
		<difficult>0</difficult>
		<bndbox>
			<xmin>3581</xmin>
			<ymin>1861</ymin>
			<xmax>3694</xmax>
			<ymax>2024</ymax>
		</bndbox>
	</object>
	<object>
		<name>0</name>
		<pose>Unspecified</pose>
		<truncated>0</truncated>
		<difficult>0</difficult>
		<bndbox>
			<xmin>3312</xmin>
			<ymin>1855</ymin>
			<xmax>3437</xmax>
			<ymax>1993</ymax>
		</bndbox>
	</object>
	<object>
		<name>0</name>
		<pose>Unspecified</pose>
		<truncated>0</truncated>
		<difficult>0</difficult>
		<bndbox>
			<xmin>3025</xmin>
			<ymin>1868</ymin>
			<xmax>3131</xmax>
			<ymax>2011</ymax>
		</bndbox>
	</object>
	<object>
		<name>0</name>
		<pose>Unspecified</pose>
		<truncated>0</truncated>
		<difficult>0</difficult>
		<bndbox>
			<xmin>2769</xmin>
			<ymin>1899</ymin>
			<xmax>2881</xmax>
			<ymax>2024</ymax>
		</bndbox>
	</object>
	<object>
		<name>0</name>
		<pose>Unspecified</pose>
		<truncated>0</truncated>
		<difficult>0</difficult>
		<bndbox>
			<xmin>2506</xmin>
			<ymin>1893</ymin>
			<xmax>2612</xmax>
			<ymax>2055</ymax>
		</bndbox>
	</object>
	<object>
		<name>0</name>
		<pose>Unspecified</pose>
		<truncated>0</truncated>
		<difficult>0</difficult>
		<bndbox>
			<xmin>2187</xmin>
			<ymin>1893</ymin>
			<xmax>2306</xmax>
			<ymax>2055</ymax>
		</bndbox>
	</object>
	<object>
		<name>0</name>
		<pose>Unspecified</pose>
		<truncated>0</truncated>
		<difficult>0</difficult>
		<bndbox>
			<xmin>1875</xmin>
			<ymin>1893</ymin>
			<xmax>1987</xmax>
			<ymax>2049</ymax>
		</bndbox>
	</object>
	<object>
		<name>0</name>
		<pose>Unspecified</pose>
		<truncated>0</truncated>
		<difficult>0</difficult>
		<bndbox>
			<xmin>1612</xmin>
			<ymin>1918</ymin>
			<xmax>1725</xmax>
			<ymax>2068</ymax>
		</bndbox>
	</object>
	<object>
		<name>0</name>
		<pose>Unspecified</pose>
		<truncated>0</truncated>
		<difficult>0</difficult>
		<bndbox>
			<xmin>1312</xmin>
			<ymin>1886</ymin>
			<xmax>1425</xmax>
			<ymax>2049</ymax>
		</bndbox>
	</object>
	<object>
		<name>0</name>
		<pose>Unspecified</pose>
		<truncated>0</truncated>
		<difficult>0</difficult>
		<bndbox>
			<xmin>1050</xmin>
			<ymin>1899</ymin>
			<xmax>1181</xmax>
			<ymax>2049</ymax>
		</bndbox>
	</object>
	<object>
		<name>0</name>
		<pose>Unspecified</pose>
		<truncated>0</truncated>
		<difficult>0</difficult>
		<bndbox>
			<xmin>831</xmin>
			<ymin>1905</ymin>
			<xmax>931</xmax>
			<ymax>2068</ymax>
		</bndbox>
	</object>
	<object>
		<name>0</name>
		<pose>Unspecified</pose>
		<truncated>0</truncated>
		<difficult>0</difficult>
		<bndbox>
			<xmin>594</xmin>
			<ymin>1893</ymin>
			<xmax>687</xmax>
			<ymax>2036</ymax>
		</bndbox>
	</object>
	<object>
		<name>0</name>
		<pose>Unspecified</pose>
		<truncated>0</truncated>
		<difficult>0</difficult>
		<bndbox>
			<xmin>287</xmin>
			<ymin>1899</ymin>
			<xmax>431</xmax>
			<ymax>2086</ymax>
		</bndbox>
	</object>
	<object>
		<name>0</name>
		<pose>Unspecified</pose>
		<truncated>0</truncated>
		<difficult>0</difficult>
		<bndbox>
			<xmin>287</xmin>
			<ymin>2274</ymin>
			<xmax>400</xmax>
			<ymax>2411</ymax>
		</bndbox>
	</object>
	<object>
		<name>0</name>
		<pose>Unspecified</pose>
		<truncated>0</truncated>
		<difficult>0</difficult>
		<bndbox>
			<xmin>562</xmin>
			<ymin>2255</ymin>
			<xmax>669</xmax>
			<ymax>2411</ymax>
		</bndbox>
	</object>
	<object>
		<name>0</name>
		<pose>Unspecified</pose>
		<truncated>0</truncated>
		<difficult>0</difficult>
		<bndbox>
			<xmin>825</xmin>
			<ymin>2243</ymin>
			<xmax>937</xmax>
			<ymax>2393</ymax>
		</bndbox>
	</object>
	<object>
		<name>0</name>
		<pose>Unspecified</pose>
		<truncated>0</truncated>
		<difficult>0</difficult>
		<bndbox>
			<xmin>1044</xmin>
			<ymin>2211</ymin>
			<xmax>1162</xmax>
			<ymax>2386</ymax>
		</bndbox>
	</object>
	<object>
		<name>0</name>
		<pose>Unspecified</pose>
		<truncated>0</truncated>
		<difficult>0</difficult>
		<bndbox>
			<xmin>1325</xmin>
			<ymin>2224</ymin>
			<xmax>1431</xmax>
			<ymax>2368</ymax>
		</bndbox>
	</object>
	<object>
		<name>0</name>
		<pose>Unspecified</pose>
		<truncated>0</truncated>
		<difficult>0</difficult>
		<bndbox>
			<xmin>1612</xmin>
			<ymin>2224</ymin>
			<xmax>1737</xmax>
			<ymax>2380</ymax>
		</bndbox>
	</object>
	<object>
		<name>0</name>
		<pose>Unspecified</pose>
		<truncated>0</truncated>
		<difficult>0</difficult>
		<bndbox>
			<xmin>1869</xmin>
			<ymin>2205</ymin>
			<xmax>1987</xmax>
			<ymax>2374</ymax>
		</bndbox>
	</object>
	<object>
		<name>0</name>
		<pose>Unspecified</pose>
		<truncated>0</truncated>
		<difficult>0</difficult>
		<bndbox>
			<xmin>2181</xmin>
			<ymin>2211</ymin>
			<xmax>2275</xmax>
			<ymax>2355</ymax>
		</bndbox>
	</object>
	<object>
		<name>0</name>
		<pose>Unspecified</pose>
		<truncated>0</truncated>
		<difficult>0</difficult>
		<bndbox>
			<xmin>2494</xmin>
			<ymin>2186</ymin>
			<xmax>2587</xmax>
			<ymax>2343</ymax>
		</bndbox>
	</object>
	<object>
		<name>0</name>
		<pose>Unspecified</pose>
		<truncated>0</truncated>
		<difficult>0</difficult>
		<bndbox>
			<xmin>2775</xmin>
			<ymin>2180</ymin>
			<xmax>2887</xmax>
			<ymax>2336</ymax>
		</bndbox>
	</object>
	<object>
		<name>0</name>
		<pose>Unspecified</pose>
		<truncated>0</truncated>
		<difficult>0</difficult>
		<bndbox>
			<xmin>3025</xmin>
			<ymin>2174</ymin>
			<xmax>3137</xmax>
			<ymax>2330</ymax>
		</bndbox>
	</object>
	<object>
		<name>0</name>
		<pose>Unspecified</pose>
		<truncated>0</truncated>
		<difficult>0</difficult>
		<bndbox>
			<xmin>3312</xmin>
			<ymin>2168</ymin>
			<xmax>3425</xmax>
			<ymax>2324</ymax>
		</bndbox>
	</object>
	<object>
		<name>0</name>
		<pose>Unspecified</pose>
		<truncated>0</truncated>
		<difficult>0</difficult>
		<bndbox>
			<xmin>3569</xmin>
			<ymin>2174</ymin>
			<xmax>3687</xmax>
			<ymax>2336</ymax>
		</bndbox>
	</object>
	<object>
		<name>0</name>
		<pose>Unspecified</pose>
		<truncated>0</truncated>
		<difficult>0</difficult>
		<bndbox>
			<xmin>3556</xmin>
			<ymin>2393</ymin>
			<xmax>3669</xmax>
			<ymax>2549</ymax>
		</bndbox>
	</object>
	<object>
		<name>0</name>
		<pose>Unspecified</pose>
		<truncated>0</truncated>
		<difficult>0</difficult>
		<bndbox>
			<xmin>3300</xmin>
			<ymin>2411</ymin>
			<xmax>3400</xmax>
			<ymax>2555</ymax>
		</bndbox>
	</object>
	<object>
		<name>0</name>
		<pose>Unspecified</pose>
		<truncated>0</truncated>
		<difficult>0</difficult>
		<bndbox>
			<xmin>3019</xmin>
			<ymin>2418</ymin>
			<xmax>3131</xmax>
			<ymax>2561</ymax>
		</bndbox>
	</object>
	<object>
		<name>0</name>
		<pose>Unspecified</pose>
		<truncated>0</truncated>
		<difficult>0</difficult>
		<bndbox>
			<xmin>2756</xmin>
			<ymin>2424</ymin>
			<xmax>2869</xmax>
			<ymax>2549</ymax>
		</bndbox>
	</object>
	<object>
		<name>0</name>
		<pose>Unspecified</pose>
		<truncated>0</truncated>
		<difficult>0</difficult>
		<bndbox>
			<xmin>2450</xmin>
			<ymin>2424</ymin>
			<xmax>2556</xmax>
			<ymax>2561</ymax>
		</bndbox>
	</object>
	<object>
		<name>0</name>
		<pose>Unspecified</pose>
		<truncated>0</truncated>
		<difficult>0</difficult>
		<bndbox>
			<xmin>2169</xmin>
			<ymin>2430</ymin>
			<xmax>2275</xmax>
			<ymax>2555</ymax>
		</bndbox>
	</object>
	<object>
		<name>0</name>
		<pose>Unspecified</pose>
		<truncated>0</truncated>
		<difficult>0</difficult>
		<bndbox>
			<xmin>1856</xmin>
			<ymin>2443</ymin>
			<xmax>1975</xmax>
			<ymax>2561</ymax>
		</bndbox>
	</object>
	<object>
		<name>0</name>
		<pose>Unspecified</pose>
		<truncated>0</truncated>
		<difficult>0</difficult>
		<bndbox>
			<xmin>1625</xmin>
			<ymin>2436</ymin>
			<xmax>1706</xmax>
			<ymax>2568</ymax>
		</bndbox>
	</object>
	<object>
		<name>0</name>
		<pose>Unspecified</pose>
		<truncated>0</truncated>
		<difficult>0</difficult>
		<bndbox>
			<xmin>1312</xmin>
			<ymin>2443</ymin>
			<xmax>1425</xmax>
			<ymax>2574</ymax>
		</bndbox>
	</object>
	<object>
		<name>0</name>
		<pose>Unspecified</pose>
		<truncated>0</truncated>
		<difficult>0</difficult>
		<bndbox>
			<xmin>1050</xmin>
			<ymin>2461</ymin>
			<xmax>1144</xmax>
			<ymax>2574</ymax>
		</bndbox>
	</object>
	<object>
		<name>0</name>
		<pose>Unspecified</pose>
		<truncated>0</truncated>
		<difficult>0</difficult>
		<bndbox>
			<xmin>837</xmin>
			<ymin>2468</ymin>
			<xmax>919</xmax>
			<ymax>2568</ymax>
		</bndbox>
	</object>
	<object>
		<name>0</name>
		<pose>Unspecified</pose>
		<truncated>0</truncated>
		<difficult>0</difficult>
		<bndbox>
			<xmin>556</xmin>
			<ymin>2480</ymin>
			<xmax>669</xmax>
			<ymax>2618</ymax>
		</bndbox>
	</object>
	<object>
		<name>0</name>
		<pose>Unspecified</pose>
		<truncated>0</truncated>
		<difficult>0</difficult>
		<bndbox>
			<xmin>300</xmin>
			<ymin>2480</ymin>
			<xmax>394</xmax>
			<ymax>2593</ymax>
		</bndbox>
	</object>
	<object>
		<name>0</name>
		<pose>Unspecified</pose>
		<truncated>0</truncated>
		<difficult>0</difficult>
		<bndbox>
			<xmin>294</xmin>
			<ymin>2749</ymin>
			<xmax>412</xmax>
			<ymax>2874</ymax>
		</bndbox>
	</object>
	<object>
		<name>0</name>
		<pose>Unspecified</pose>
		<truncated>0</truncated>
		<difficult>0</difficult>
		<bndbox>
			<xmin>544</xmin>
			<ymin>2730</ymin>
			<xmax>669</xmax>
			<ymax>2886</ymax>
		</bndbox>
	</object>
	<object>
		<name>0</name>
		<pose>Unspecified</pose>
		<truncated>0</truncated>
		<difficult>0</difficult>
		<bndbox>
			<xmin>825</xmin>
			<ymin>2736</ymin>
			<xmax>925</xmax>
			<ymax>2880</ymax>
		</bndbox>
	</object>
	<object>
		<name>0</name>
		<pose>Unspecified</pose>
		<truncated>0</truncated>
		<difficult>0</difficult>
		<bndbox>
			<xmin>1037</xmin>
			<ymin>2718</ymin>
			<xmax>1175</xmax>
			<ymax>2868</ymax>
		</bndbox>
	</object>
	<object>
		<name>0</name>
		<pose>Unspecified</pose>
		<truncated>0</truncated>
		<difficult>0</difficult>
		<bndbox>
			<xmin>1300</xmin>
			<ymin>2718</ymin>
			<xmax>1425</xmax>
			<ymax>2861</ymax>
		</bndbox>
	</object>
	<object>
		<name>0</name>
		<pose>Unspecified</pose>
		<truncated>0</truncated>
		<difficult>0</difficult>
		<bndbox>
			<xmin>1581</xmin>
			<ymin>2705</ymin>
			<xmax>1687</xmax>
			<ymax>2849</ymax>
		</bndbox>
	</object>
	<object>
		<name>0</name>
		<pose>Unspecified</pose>
		<truncated>0</truncated>
		<difficult>0</difficult>
		<bndbox>
			<xmin>1875</xmin>
			<ymin>2699</ymin>
			<xmax>1987</xmax>
			<ymax>2836</ymax>
		</bndbox>
	</object>
	<object>
		<name>0</name>
		<pose>Unspecified</pose>
		<truncated>0</truncated>
		<difficult>0</difficult>
		<bndbox>
			<xmin>2150</xmin>
			<ymin>2693</ymin>
			<xmax>2256</xmax>
			<ymax>2818</ymax>
		</bndbox>
	</object>
	<object>
		<name>0</name>
		<pose>Unspecified</pose>
		<truncated>0</truncated>
		<difficult>0</difficult>
		<bndbox>
			<xmin>2450</xmin>
			<ymin>2668</ymin>
			<xmax>2556</xmax>
			<ymax>2811</ymax>
		</bndbox>
	</object>
	<object>
		<name>0</name>
		<pose>Unspecified</pose>
		<truncated>0</truncated>
		<difficult>0</difficult>
		<bndbox>
			<xmin>2750</xmin>
			<ymin>2655</ymin>
			<xmax>2862</xmax>
			<ymax>2824</ymax>
		</bndbox>
	</object>
	<object>
		<name>0</name>
		<pose>Unspecified</pose>
		<truncated>0</truncated>
		<difficult>0</difficult>
		<bndbox>
			<xmin>3037</xmin>
			<ymin>2661</ymin>
			<xmax>3162</xmax>
			<ymax>2811</ymax>
		</bndbox>
	</object>
	<object>
		<name>0</name>
		<pose>Unspecified</pose>
		<truncated>0</truncated>
		<difficult>0</difficult>
		<bndbox>
			<xmin>3294</xmin>
			<ymin>2661</ymin>
			<xmax>3406</xmax>
			<ymax>2805</ymax>
		</bndbox>
	</object>
	<object>
		<name>0</name>
		<pose>Unspecified</pose>
		<truncated>0</truncated>
		<difficult>0</difficult>
		<bndbox>
			<xmin>3562</xmin>
			<ymin>2661</ymin>
			<xmax>3675</xmax>
			<ymax>2805</ymax>
		</bndbox>
	</object>
</annotation>
